{
 "title": "重要提示！",
 "content": "僵尸马披风获得已结束，现在官方正在向有资格的玩家发送邮件，如果您到目前还没有收到邮件请前往：https://help.minecraft.net/hc/en-us 进行人工申诉并附上击杀证据",
 "img": "https://blockcarft4979.github.io/app_update/img/84e1e664796df1f7fe558ef25a602d8318579964.jpg",
 "music": {
  "url": "files\/Hits Different(Explicit) - Taylor Swift.mp3",
  "cover": "files\/Hits Different(Explicit) - Taylor Swift.jpg",
  "title": "Hits Different",
  "artist": "Taylor Swift"
 },
 "link": "https:\/\/blockcarft4979.github.io\/app_update\/announcement.html"
}